tree_sitter_python_language/__init__.py
tree_sitter_python_language/__main__.py
tree_sitter_python_language/python-language.so
tree_sitter_python_language-0.0.0.dist-info/METADATA
tree_sitter_python_language-0.0.0.dist-info/WHEEL
tree_sitter_python_language-0.0.0.dist-info/top_level.txt
tree_sitter_python_language-0.0.0.dist-info/RECORD
