Metadata-Version: 2.1
Name: tree-sitter-python-language
Version: 0.0.0
Summary: UNKNOWN
License: UNKNOWN
Platform: UNKNOWN
Requires-Dist: tree-sitter
